Metadata-Version: 2.1
Name: distributions-jcab
Version: 0.1
Summary: Gaussian distributions
